medical/__init__.py
medical/admin.py
medical/apps.py
medical/exceptions.py
medical/gql_mutations.py
medical/gql_queries.py
medical/models.py
medical/schema.py
medical/services.py
medical/test_helpers.py
medical/tests_api.py
medical/urls.py
medical/utils.py
medical/views.py
medical/migrations/0001_initial.py
medical/migrations/0002_diagnosis.py
medical/migrations/0003_mutations.py
medical/migrations/0004_add_missing_fields.py
medical/migrations/0005_set_managed_to_true.py
medical/migrations/0006_auto_20230718_1332.py
medical/migrations/0007_alter_item_maximum_amount_alter_item_quantity_and_more.py
medical/migrations/0008_auto_20220804_1112.py
medical/migrations/0009_alter_service_patient_category.py
medical/migrations/0010_rename_servicelinkeditem_serviceitem_parent_and_more.py
medical/migrations/__init__.py
openimis_be_medical-1.10.0.dist-info/licenses/LICENSE.md
openimis_be_medical-1.10.0.dist-info/METADATA
openimis_be_medical-1.10.0.dist-info/WHEEL
openimis_be_medical-1.10.0.dist-info/top_level.txt
openimis_be_medical-1.10.0.dist-info/RECORD
